compdb/__about__.py
compdb/__init__.py
compdb/__main__.py
compdb/cli.py
compdb/config.py
compdb/core.py
compdb/filelist.py
compdb/includedb.py
compdb/models.py
compdb/utils.py
compdb/backend/__init__.py
compdb/backend/json.py
compdb/backend/memory.py
compdb/complementer/__init__.py
compdb/complementer/headerdb.py
compdb-0.2.0.dist-info/DESCRIPTION.rst
compdb-0.2.0.dist-info/METADATA
compdb-0.2.0.dist-info/RECORD
compdb-0.2.0.dist-info/WHEEL
compdb-0.2.0.dist-info/entry_points.txt
compdb-0.2.0.dist-info/metadata.json
compdb-0.2.0.dist-info/top_level.txt
