Metadata-Version: 2.0
Name: compdb
Version: 0.2.0
Summary: The compilation database Swiss army knife
Home-page: https://github.com/Sarcasm/compdb
Author: Guillaume Papin
Author-email: guillaume.papin@epitech.eu
License: MIT
Keywords: Clang,compilation-database,compdb
Platform: UNKNOWN
Classifier: Development Status :: 3 - Alpha
Classifier: Intended Audience :: Developers
Classifier: Topic :: Software Development :: Build Tools
Classifier: License :: OSI Approved :: MIT License
Classifier: Programming Language :: Python :: 2
Classifier: Programming Language :: Python :: 2.7
Classifier: Programming Language :: Python :: 3
Classifier: Programming Language :: Python :: 3.3
Classifier: Programming Language :: Python :: 3.4
Classifier: Programming Language :: Python :: 3.5
Classifier: Programming Language :: Python :: 3.6
Classifier: Programming Language :: Python :: Implementation :: PyPy
Requires-Python: >=2.7,!=3.0.*,!=3.1.*,!=3.2.*
Requires-Dist: configparser; python_version<'3.0'
